CHANGELOG
LICENSE
MANIFEST.in
README.rst
setup.nsi
setup.py
gayeogi/__init__.py
gayeogi/main.py
gayeogi.egg-info/PKG-INFO
gayeogi.egg-info/SOURCES.txt
gayeogi.egg-info/dependency_links.txt
gayeogi.egg-info/requires.txt
gayeogi.egg-info/top_level.txt
gayeogi/db/__init__.py
gayeogi/db/bandsensor.py
gayeogi/db/distributor.py
gayeogi/db/local.py
gayeogi/db/utils.py
gayeogi/db/bees/__init__.py
gayeogi/db/bees/beeexceptions.py
gayeogi/db/bees/metalArchives.py
gayeogi/db/bees/musicbrainz.py
gayeogi/db/bees/progarchives.py
gayeogi/interfaces/__init__.py
gayeogi/interfaces/confirmation.py
gayeogi/interfaces/main.py
gayeogi/interfaces/settings.py
gayeogi/plugins/__init__.py
gayeogi/plugins/lastfm.py
gayeogi/plugins/logs.py
gayeogi/plugins/mpris.py
gayeogi/plugins/player.py
scripts/gayeogi
scripts/gayeogi.desktop