Metadata-Version: 1.0
Name: gayeogi
Version: 0.6.3
Summary: A fully-featured music management suite.
Home-page: http://github.com/KenjiTakahashi/gayeogi
Author: Karol "Kenji Takahashi" Woźniak
Author-email: wozniakk@gmail.com
License: GPL3
Platform: UNKNOWN
Classifier: Development Status :: 4 - Beta
Classifier: Environment :: Win32 (MS Windows)
Classifier: Environment :: X11 Applications :: Qt
Classifier: Intended Audience :: End Users/Desktop
Classifier: License :: OSI Approved :: GNU General Public License (GPL)
Classifier: Natural Language :: English
Classifier: Natural Language :: Polish
Classifier: Operating System :: OS Independent
Classifier: Programming Language :: Python :: 2
Classifier: Topic :: Multimedia :: Sound/Audio :: Players
